{
  "stem": "PachangaEdited__Ronde_Pachanga_Drill",
  "translations": {
    "ar": {
      "1": "حسناً، الآن سنبدأ بالتدرب\nمع Ronde",
      "2": "de Jambs ببطء، جاهزون؟",
      "3": "5 6 7، و",
      "4": "Pachanga، Ronde، Pachanga، Ronde،\nPachanga،",
      "5": "Ronde، Pachanga،",
      "6": "Ronde، و.",
      "7": "Pa!",
      "8": "الآن سنذهب أسرع، جاهزون؟",
      "9": "Cha، boom، cha، boom، cha، boom، cha، ميلوا\nبعيداً، cha،",
      "10": "boom، cha، boom، cha، boom، cha،",
      "11": "Boom، cha، boom، cha، boom،",
      "12": "cha، boom، cha، boom، cha،",
      "13": "boom، cha، boom،",
      "14": "cha، boom، cha، boom،",
      "15": "Cha، boom، cha، boom، cha، boom، cha،\nboom، cha، boom،",
      "16": "cha، boom، cha، boom، cha، boom، cha،\nboom،",
      "17": "Cha، boom، cha، boom، cha، boom، cha،\nboom، cha، boom،",
      "18": "cha، boom، cha، boom، cha، boom، cha،\nboom،",
      "19": "Cha، boom، cha، boom، cha، boom، cha،\nboom، cha، boom،",
      "20": "cha، boom، cha، boom، cha، boom، cha،\nboom، cha، boom، ya،",
      "21": "وارفعوا، chop، woo، chop، woo، chop،\nwoo، chop، انهضوا",
      "22": "للأعلى، chop، chop،",
      "23": "Chop، تجمعوا،",
      "24": "وافعلوا monkey soul.",
      "25": "حسناً، الآن سنفعل Juan\nMatos، أنتم",
      "26": "جاهزون؟",
      "27": "ببطء، 5 6 7، و1 2 3، أربعة، خمسة، ستة،\nالآن مع",
      "28": "Bounce، و1 2 3، أربعة، مع الورك، ستة،\nسبعة، ثمانية،",
      "29": "متحركون.",
      "30": "الآن فلنحاول بسرعة، واحد، ثلاثة، خمسة،\nسبعة، واحد، ثلاثة،",
      "31": "خمسة، تسعة، سبعة، واحد، ثلاثة، خمسة،\nسبعة، واحد، ثلاثة،",
      "32": "افتحوا الأذرع.",
      "33": "الآن فلنحاول مع",
      "34": "5 6 7، ثمانية، واحد، ثلاثة،",
      "35": "أربعة، و",
      "36": "جيد جداً.",
      "37": "حسناً، Juan Matos مرة أخرى،\nجاهزون؟",
      "38": "سبعة، ثمانية، 1 2 3، أربعة،",
      "39": "خمسة، ستة، الآن نقوم بـBounce، واحد،",
      "40": "اثنان، نزولاً، صعوداً، نزولاً، صعوداً،",
      "41": "الآن مع الورك، chop،",
      "42": "الآن مع الجسم كله، واحد، ثلاثة، خمسة،\nسبعة، الآن",
      "43": "فلنجرب وقتنا.",
      "44": "جاهزون؟",
      "45": "5 6 7، ثمانية، خمسة، سبعة، نزولاً، نزولاً،\nنزولاً، نزولاً، نزولاً،",
      "46": "ارتاحوا.",
      "47": "الآن افتحوا الأذرع، آه،",
      "48": "آه، الآن، chop، خمسة، ستة، مرة أخرى،",
      "49": "وchop.",
      "50": "Woo!",
      "51": "آه، woo!",
      "52": "آه!",
      "53": "هذه حفرة!",
      "54": "Woo!",
      "55": "الآن افتحوا الأذرع.",
      "56": "إنها يداك،volehead، youydi.",
      "57": "تعرفون أنا أكتب يداكم هنا في الأعلى\nعبر الجانب",
      "58": "المظلم.",
      "59": "يمكنكم الرؤية عبر الجانب المظلم—و؟",
      "60": "يمكنكم الرؤية عبر الجانب المظلم—he Здесь\nis كيف",
      "61": "كونوا هنا،ilee armour picture—هذا\nسبب لي، لذا أنا",
      "62": "هذا حقاً جيد، حبي.",
      "63": "إنها منطقة رائعة للنوم لأنكم\nكنتم.",
      "64": "كنا ندفع.",
      "65": "هذه منطقة رائعة لفهم…",
      "66": "أنتم يمكنكم تجربتكم هناك!",
      "67": "ولطالما كنا نبقى t Release!",
      "68": "أوه واو!",
      "69": "الباب الذي v يدعوكم لديكم صديق صحي،\nهذا",
      "70": "المجتمع…",
      "71": "خذوها، استخدموني، جميل!",
      "72": "نعم!",
      "73": "عدوان!",
      "74": "ثم الغرفة التي ستذهب لاستخدامها قيلت\nبشكل جيد."
    },
    "el": {
      "1": "Εντάξει, τώρα θα αρχίσουμε να εξασκούμαστε\nμε το Ronde",
      "2": "de Jambs αργά, έτοιμοι;",
      "3": "5 6 7, και",
      "4": "Pachanga, Ronde, Pachanga, Ronde,\nPachanga,",
      "5": "Ronde, Pachanga,",
      "6": "Ronde, και.",
      "7": "Pa!",
      "8": "Τώρα θα πάμε πιο γρήγορα, έτοιμοι;",
      "9": "Cha, boom, cha, boom, cha, boom, cha, γείρετε\nμακριά, cha,",
      "10": "boom, cha, boom, cha, boom, cha,",
      "11": "Boom, cha, boom, cha, boom,",
      "12": "cha, boom, cha, boom, cha,",
      "13": "boom, cha, boom,",
      "14": "cha, boom, cha, boom,",
      "15": "Cha, boom, cha, boom, cha, boom, cha,\nboom, cha, boom,",
      "16": "cha, boom, cha, boom, cha, boom, cha,\nboom,",
      "17": "Cha, boom, cha, boom, cha, boom, cha,\nboom, cha, boom,",
      "18": "cha, boom, cha, boom, cha, boom, cha,\nboom,",
      "19": "Cha, boom, cha, boom, cha, boom, cha,\nboom, cha, boom,",
      "20": "cha, boom, cha, boom, cha, boom, cha,\nboom, cha, boom, ya,",
      "21": "Και σηκωθείτε, chop, woo, chop, woo, chop,\nwoo, chop, σηκωθείτε",
      "22": "πάνω, chop, chop,",
      "23": "Chop, συγκεντρωθείτε,",
      "24": "και κάντε monkey soul.",
      "25": "Εντάξει, τώρα θα κάνουμε το Juan\nMatos, είστε",
      "26": "έτοιμοι;",
      "27": "Αργά, 5 6 7, και 1 2 3, τέσσερα, πέντε, έξι,\nτώρα με",
      "28": "Bounce, και 1 2 3, τέσσερα, με γοφό, έξι,\nεπτά, οκτώ,",
      "29": "κινούμενοι.",
      "30": "Τώρα ας δοκιμάσουμε γρήγορα, ένα, τρία, πέντε,\nεπτά, ένα, τρία,",
      "31": "πέντε, εννέα, επτά, ένα, τρία, πέντε,\nεπτά, ένα, τρία,",
      "32": "ανοίξτε τα χέρια.",
      "33": "Τώρα ας δοκιμάσουμε με το μικρό",
      "34": "5 6 7, οκτώ, ένα, τρία,",
      "35": "τέσσερα, και",
      "36": "πολύ καλά.",
      "37": "Εντάξει, Juan Matos μία ακόμα φορά,\nέτοιμοι;",
      "38": "Επτά, οκτώ, 1 2 3, τέσσερα,",
      "39": "πέντε, έξι, τώρα κάνουμε Bounce, ένα,",
      "40": "δύο, κάτω, πάνω, κάτω, πάνω,",
      "41": "τώρα με γοφό, chop,",
      "42": "Τώρα με όλο το σώμα, ένα, τρία, πέντε,\nεπτά, τώρα",
      "43": "ας το δοκιμάσουμε στον χρόνο μας.",
      "44": "Έτοιμοι;",
      "45": "5 6 7, οκτώ, πέντε, επτά, κάτω, κάτω,\nκάτω, κάτω, κάτω,",
      "46": "χαλαρώστε.",
      "47": "Τώρα ανοίξτε τα χέρια, α,",
      "48": "α, τώρα, chop, πέντε, έξι, ξανά,",
      "49": "και chop.",
      "50": "Woo!",
      "51": "Α, woo!",
      "52": "Α!",
      "53": "Αυτή είναι μια τρύπα!",
      "54": "Woo!",
      "55": "Τώρα ανοίξτε τα χέρια.",
      "56": "Είναι τα χέρια σας,volehead, youydi.",
      "57": "Ξέρετε γράφω τα χέρια σας εδώ πάνω\nμέσω της σκοτεινής",
      "58": "πλευράς.",
      "59": "Μπορείτε να δείτε μέσω της σκοτεινής πλευράς—και;",
      "60": "Μπορείτε να δείτε μέσω της σκοτεινής πλευράς—he Здесь\nis πώς",
      "61": "Να είστε εδώ,ilee armour picture—αυτό είναι\nαιτία για μένα, οπότε εγώ",
      "62": "Αυτό είναι πραγματικά καλό, αγάπη.",
      "63": "Είναι μια ωραία περιοχή για ύπνο επειδή έχετε\nήταν.",
      "64": "Σπρώχναμε.",
      "65": "Αυτή είναι μια ωραία περιοχή για κατανόηση…",
      "66": "Εσύ μπορεί να σας βιώσει εκεί!",
      "67": "Και πάντα μένουμε t Release!",
      "68": "Ω wow!",
      "69": "Η πόρτα που v σας καλεί έχετε έναν υγιή\nφίλο, αυτή",
      "70": "η κοινότητα…",
      "71": "Πάρτε το, χρησιμοποιήστε με, όμορφο!",
      "72": "Ναι!",
      "73": "Δύο εχθροί!",
      "74": "Και μετά το δωμάτιο που θα χρησιμοποιηθεί\nειπώθηκε καλά."
    }
  }
}
