{
  "stem": "Mambo101Edited__Styling_1_Lesson_1",
  "translations": {
    "ar": {
      "1": "حسنًا يا شباب، أهلًا بكم في هذه الوحدة\nالأولى عن Styling.",
      "2": "الآن، هذا هو الصف حيث سنشرح أخيرًا",
      "3": "الذراعين.",
      "4": "وما الذي سنفعله بهذه\nالذراعين، حسنًا؟",
      "5": "لذا هنا عمدًا، كنت أركّز فقط على\nالقدمين.",
      "6": "القدمين.",
      "7": "لأنه من المهم جدًا أن نحصل على\nالأساسيات",
      "8": "أولًا،",
      "9": "وهي Footwork والتأكد من أننا\nنغيّر",
      "10": "وزننا.",
      "11": "ومرة أخرى أن جسمنا، مركز كتلتنا\nدائمًا فوق",
      "12": "قدمينا.",
      "13": "عندما نخطو دائمًا تحت أنفسنا،\nحسنًا؟",
      "14": "هذا هو الأساس الأول.",
      "15": "الآن، يمكننا البدء بإدخال بعض الذراعين.",
      "16": "الآن، أحب الذهاب مع الذراعين أولًا ثم\nإدخال",
      "17": "المزيد من الجسم العلوي قليلًا.",
      "18": "لأن حقًا عندما ترقص Mambo وحقًا عندما",
      "19": "تعود إلى الأيام،",
      "20": "الكثير من هذا يأتي من رقص jazz.",
      "21": "وترى أنهم لا يستخدمون كثيرًا Body Movement",
      "22": "الذي نستخدمه في Salsa.",
      "23": "لذا حقًا، يمكنك أن ترقص Salsa جيدًا جدًا\nبمعرفة",
      "24": "Footwork الخاص بك.",
      "25": "وأكثر أو أقل ماذا تفعل بـ\nذراعيك.",
      "26": "وثم عندما يكون لديك ذلك، يمكنك إضافة\nبقدر ما تريد من Body",
      "27": "Movement.",
      "28": "وبقدر ما تريد من التعقيد.",
      "29": "لكن حقًا، أريدك أن تعطي شيئًا\nبسيطًا يمكنك",
      "30": "فعله بيديك في الوقت الحالي.",
      "31": "حسنًا، سنركّز على التقنية\nالأولى",
      "32": "للذراعين،",
      "33": "وهي تقنية Mambo وتأتي من",
      "34": "palladium.",
      "35": "لذا هذه أكثر من الأمام والخلف مقابل\nSalsa،",
      "36": "التي هي أكثر جانبية.",
      "37": "يستخدمون نفس التقنية.",
      "38": "ومع ذلك، اللكنة مختلفة قليلًا وبوضوح\nأن",
      "39": "الاتجاه مختلف.",
      "40": "هذه بالنسبة لي أبسط قليلًا ولدينا",
      "41": "ذقنا منها بالفعل.",
      "42": "مع هذه الخطوات هنا.",
      "43": "لكن الآن سأشرح المزيد قليلًا من\nالتقنية.",
      "44": "التقنية.",
      "45": "لذا قلت لك فقط ارفع ذراعيك للأعلى وللأسفل،\nلكن",
      "46": "إنها أكثر تعقيدًا قليلًا.",
      "47": "لذا الحركة تذهب قليلًا مثل، تعرف،\nتلك",
      "48": "قضبان قطار choo-choo.",
      "49": "هذه هي الحركة التي ستفعلها",
      "50": "بذراعك.",
      "51": "الآن سأشرحها لك لأن الكثير من",
      "52": "الناس لا يفهمون حقًا.",
      "53": "ماذا يعني هذا لفعل هذه الحركة.",
      "54": "ما يعنيه هو أن أولًا ستذهب بـ",
      "55": "كوعك.",
      "56": "وثم ستمدّ الكوع وستذهب",
      "57": "للأسفل.",
      "58": "لذا فكّر، ارفع كوعك، ثم مدّ\nاليد واذهب",
      "59": "للأسفل.",
      "60": "سنتدرّب على هذه الحركة هنا فقط.",
      "61": "وعندما تفعلها بكلتا اليدين، تكون كأنك",
      "62": "تأخذ صخرة كبيرة.",
      "63": "وتحتاج إلى رفعها فوق قضيب وستـ",
      "64": "ترفعها فوق هذا.",
      "65": "تعرف، هؤلاء متسابقي strongman الذين\nيأخذون تلك الصخور",
      "66": "الكبيرة ويضعونها فوق قضيب.",
      "67": "إنها قليلًا مثل ذلك، لكننا لن\nنستخدم",
      "68": "كامل الجسم.",
      "69": "هذا فقط التقاط صندوق ووضعه\nعلى رف.",
      "70": "لنجرّبها. 5 6 7.",
      "71": "والتقط الصندوق، ضعه على الرف.",
      "72": "5 6 7.",
      "73": "و 1، ثلاثة، خمسة، سبعة.",
      "74": "و 1، ثلاثة، خمسة، سبعة.",
      "75": "و 1، ثلاثة، خمسة.",
      "76": "ترى كيف تذهب أكواعي ثم تمتدّ هنا\nمن الكوع.",
      "77": "سأمدّ يديّ.",
      "78": "هذا مثل رمي سهم.",
      "79": "جيد جدًا.",
      "80": "الآن سنفعل هذا، لكن ذراعًا واحدة في\nالمرة.",
      "81": "وكيف ستعمل؟",
      "82": "ستكون دائمًا اليد المعاكسة\nلساقي.",
      "83": "حسنًا؟",
      "84": "لذا أذهب بالساق اليمنى.",
      "85": "سأذهب بالذراع اليسرى.",
      "86": "لذا سأذهب 5 6 7.",
      "87": "1 2 3.",
      "88": "حسنًا؟",
      "89": "5 6 7.",
      "90": "و 1 2 3.",
      "91": "ترى أن هناك لكنة قليلًا على هذا\nالـ count الأمامي.",
      "92": "لذا عندما أمدّ، هناك لكنة قليلًا\nهنا.",
      "93": "هذا ما أريدك أن تفكّر به وهو\nالإسقاط للأمام.",
      "94": "لذا بدلًا من فعلها هكذا فقط، تأكّد\nأنك",
      "95": "تفعل الحركة الكاملة.",
      "96": "تأتي للأعلى.",
      "97": "تسقط للأمام.",
      "98": "وثم ترتاح.",
      "99": "تنزل ذراعك.",
      "100": "حسنًا؟",
      "101": "5 6 7.",
      "102": "1 2 3.",
      "103": "و 5 6 7.",
      "104": "و 1 2 3.",
      "105": "و 5 6 7.",
      "106": "و 1 2 3.",
      "107": "و 5 6 7.",
      "108": "حسنًا؟",
      "109": "الآن سنفعلها مع Footwork الخاص بنا.",
      "110": "5 6 7.",
      "111": "و 1 2 3.",
      "112": "و 5 6 7.",
      "113": "و 1 2 3.",
      "114": "5 6 7.",
      "115": "1 2 3.",
      "116": "و 5 6 7.",
      "117": "عندما تجلس إلى الجانب.",
      "118": "1 2 3.",
      "119": "خمسة.",
      "120": "ترى أن لديك هذه الحركة حيث كوعك سـ",
      "121": "يأتي أولًا.",
      "122": "وثم ستمدّ.",
      "123": "ثم ستذهب للأسفل.",
      "124": "وستكرّر.",
      "125": "اليدان.",
      "126": "حركة قطار choo-choo.",
      "127": "الآن في الأيام السابقة في Palladium،\nلم يعرفوا حقًا",
      "128": "كيف يحرّكون أذرعهم.",
      "129": "لم يعرفوا حقًا ماذا يفعلون بـ\nأذرعهم.",
      "130": "وضع في الاعتبار، هؤلاء كانوا راقصين لم",
      "131": "يكونوا مدرّبين بشكل كلاسيكي.",
      "132": "لكن كان لديهم الكثير من النمط.",
      "133": "الكثير من النكهات.",
      "134": "لذا كانوا يرقصون هكذا بـ\nأذرعهم.",
      "135": "ولم يعرفوا حقًا ماذا يفعلون\nبالضبط.",
      "136": "لم يكن لديهم التقنية الصحيحة.",
      "137": "لكنهم لا يزالون يجعلونها تبدو رائعة.",
      "138": "لذا حقًا، أنصحك أن تتدرّب قليلًا على\nهذه",
      "139": "في الأساسية.",
      "140": "والآن، حاول وافعل Suzy Qs الخاصة بك.",
      "141": "1 2 3، 5 6 7.",
      "142": "وتذكّر، هذا يمين، يسار، يمين\nبالأيدي.",
      "143": "يسار، يمين، يسار.",
      "144": "وربما دوراتك.",
      "145": "1 2 3، 5 6 7.",
      "146": "ربما Left Turn الخاصة بك.",
      "147": "1 2 3.",
      "148": "يمين، يسار، يمين.",
      "149": "أساسي.",
      "150": "اثنان، ثلاثة، 5 6 7.",
      "151": "حسنًا؟",
      "152": "حسنًا.",
      "153": "سنتدرّب على فعل هذه الحركة\nأكثر",
      "154": "قليلًا.",
      "155": "ومرة أخرى، أدعوك للذهاب الآن على كل\nالخطوات",
      "156": "التي غطّيناها.",
      "157": "أعد فقط الدريلات.",
      "158": "وحاول وضع تلك الذراعين على\nكل هذه الخطوات.",
      "159": "لذا، 5 6 7.",
      "160": "فقط الذراعين.",
      "161": "1 2 3.",
      "162": "وكوع، يد.",
      "163": "كوع، يد.",
      "164": "كوع، يد.",
      "165": "سبعة.",
      "166": "و 1 2 3.",
      "167": "خمسة، ستة.",
      "168": "مع الخطوة.",
      "169": "و 1 2 3.",
      "170": "5 6 7.",
      "171": "تأكّد من أن وضعك للأمام\nقليلًا.",
      "172": "ستة، سبعة.",
      "173": "1 2 3.",
      "174": "5 6 7.",
      "175": "1 2 3.",
      "176": "5 6 7.",
      "177": "1 2 3.",
      "178": "5 6 7.",
      "179": "1 2 3.",
      "180": "5 6 7.",
      "181": "1 2 3.",
      "182": "5 6 7.",
      "183": "جيد جدًا، سنفعلها مرة أخرى، لكن\nتأكّد الآن",
      "184": "سنذهب جانبًا فقط للتأكد من\nأن.",
      "185": "هذا الكوع لا يأتي خلف الظهر أبدًا. هذا\nخطأ آخر",
      "186": "أراه كثيرًا، هؤلاء الناس يرقصون.",
      "187": "هكذا، والآن يبدو قليلًا كأنني",
      "188": "أسبح، لكننا لا نسبح، نحن دائمًا.",
      "189": "نبقي أكواعنا أمام جسمنا.\nهذا يسمى",
      "190": "المستوى السهمي، وعمومًا عندما.",
      "191": "ترقص حوالي 99.999% من الوقت،\nستـ",
      "192": "تبقي كل حركات ذراعك في\nالسهمي.",
      "193": "Plane، لذا هنا لا تتجاوز أبدًا\nهذا النطاق",
      "194": "من الحركة، حسنًا؟ لذا حقًا أدعوك أن.",
      "195": "تفكّر للأمام، هذا حيث تكون كل\nطاقتك عندما",
      "196": "ترقص Salsa. لذا لنفعلها، خمسة، ستة،",
      "197": "سبعة، 1 2 3، 5 6 7. لاحظ صدري قليلًا",
      "198": "للأمام، 5 6 7،",
      "199": "1 2 3، 5 6 7، 1 2 3، 5 6 7. جيد جدًا،\nلنفعلها مرة",
      "200": "أخرى.",
      "201": "5 6 7، أساسي، 1 2 3،",
      "202": "الذراعان تذهب سبعة، يسار، يمين، يسار،",
      "203": "يمين،",
      "204": "يسار، يمين.",
      "205": "أساسًا إنها معارضة بين الذراعين\nوالقدمين.",
      "206": "و 1 2 3، 5 6 7، واحد، اثنان،",
      "207": "ثلاثة، يمكنك أن تتخيّل أنك\nترمي سهمًا. 1 2 3،",
      "208": "5 6 7، 1 2 3.",
      "209": "أبقِ أكواعك أمام",
      "210": "جسمك في المستوى السهمي",
      "211": "plane. ثلاثة، خمسة، ستة، مرة\nأخرى.",
      "212": "1 2 3، 5 6 7."
    },
    "el": {
      "1": "Εντάξει παιδιά, καλώς ήρθατε σε αυτή την πρώτη\nενότητα για το Styling.",
      "2": "Τώρα, αυτό είναι το μάθημα όπου θα\nαναλύσουμε επιτέλους",
      "3": "τα χέρια.",
      "4": "Και τι θα κάνουμε με αυτά\nτα χέρια, εντάξει;",
      "5": "Άρα εδώ επίτηδες, εστίαζα μόνο πραγματικά\nστα",
      "6": "πόδια.",
      "7": "Γιατί είναι πολύ σημαντικό να αποκτήσουμε τα\nθεμέλια",
      "8": "πρώτα,",
      "9": "Που είναι το Footwork και να βεβαιωθούμε ότι\nαλλάζουμε",
      "10": "βάρος.",
      "11": "Και πάλι ότι το σώμα μας, το κέντρο μάζας μας\nείναι πάντα όλο",
      "12": "πάνω από τα πόδια μας.",
      "13": "Όταν πάντα πατάμε κάτω από τους εαυτούς μας,\nεντάξει;",
      "14": "Αυτό είναι το πρώτο θεμέλιο.",
      "15": "Τώρα, μπορούμε να αρχίσουμε να εισάγουμε λίγα χέρια.",
      "16": "Τώρα, μου αρέσει να πάω με τα χέρια πρώτα και\nμετά να εισάγω",
      "17": "λίγο πιο πολύ από το πάνω σώμα.",
      "18": "Γιατί πραγματικά όταν χορεύεις Mambo και πραγματικά όταν",
      "19": "πας πίσω στις μέρες,",
      "20": "Πολλά από αυτά προέρχονται από χορό jazz.",
      "21": "Και βλέπεις δεν χρησιμοποιούν τόσο πολύ Body Movement",
      "22": "που χρησιμοποιούμε στη Salsa.",
      "23": "Άρα πραγματικά, μπορείς να χορέψεις Salsa πολύ καλά\nξέροντας το",
      "24": "Footwork σου.",
      "25": "Και λίγο πολύ τι να κάνεις με τα\nχέρια σου.",
      "26": "Και μετά όταν έχεις αυτό, μπορείς να προσθέσεις\nόσο Body",
      "27": "Movement.",
      "28": "Και όση πολυπλοκότητα θέλεις.",
      "29": "Αλλά πραγματικά, θέλω να δώσεις κάτι\nαπλό που μπορείς",
      "30": "να κάνεις με τα χέρια σου προς το παρόν.",
      "31": "Εντάξει, θα εστιάσουμε στην πρώτη\nτεχνική",
      "32": "για τα χέρια,",
      "33": "Που θα είναι η τεχνική Mambo και προέρχεται από",
      "34": "το palladium.",
      "35": "Άρα αυτή είναι πολύ πιο μπροστά και πίσω σε σύγκριση\nμε τη Salsa,",
      "36": "που είναι πιο πλάγια.",
      "37": "Χρησιμοποιούν την ίδια τεχνική.",
      "38": "Ωστόσο, η έμφαση είναι λίγο διαφορετική και προφανώς αυτή",
      "39": "η κατεύθυνση είναι διαφορετική.",
      "40": "Αυτή για μένα είναι λίγο πιο απλή και\nέχουμε",
      "41": "ήδη πάρει μια γεύση.",
      "42": "Με αυτά τα βήματα εδώ.",
      "43": "Αλλά τώρα θα αναλύσω λίγο πιο πολύ από\nτην",
      "44": "τεχνική.",
      "45": "Άρα σου είπα να σηκώσεις απλά τα χέρια σου πάνω και κάτω, αλλά",
      "46": "είναι λίγο πιο πολύπλοκο.",
      "47": "Άρα η κίνηση πάει λίγο σαν, ξέρεις, εκείνες\nτις",
      "48": "ράγες τρένου choo-choo.",
      "49": "Αυτή είναι η κίνηση που θα κάνεις",
      "50": "με το χέρι σου.",
      "51": "Τώρα θα την αναλύσω για σένα γιατί πολλοί",
      "52": "άνθρωποι δεν καταλαβαίνουν πραγματικά.",
      "53": "Τι σημαίνει να κάνεις αυτή την κίνηση.",
      "54": "Αυτό που σημαίνει είναι ότι πρώτα θα πας με",
      "55": "τον αγκώνα σου.",
      "56": "Και μετά θα τεντώσεις τον αγκώνα και θα\nπας",
      "57": "κάτω.",
      "58": "Άρα σκέψου, σήκωσε τον αγκώνα σου, μετά τέντωσε\nτο χέρι και πάνε",
      "59": "κάτω.",
      "60": "Θα εξασκηθούμε απλά σε αυτή την κίνηση εδώ.",
      "61": "Και όταν την κάνεις και με τα δύο χέρια, είναι σαν να",
      "62": "παίρνεις έναν μεγάλο βράχο.",
      "63": "Και χρειάζεται να τον περάσεις πάνω από μια μπάρα και θα\nτον",
      "64": "περάσεις πάνω από αυτό.",
      "65": "Ξέρεις, αυτοί οι strongman ανταγωνιστές που\nπαίρνουν αυτούς τους μεγάλους",
      "66": "βράχους και τους βάζουν πάνω από μια μπάρα.",
      "67": "Είναι λίγο σαν αυτό, αλλά δεν θα\nχρησιμοποιήσουμε",
      "68": "ολόκληρο το σώμα.",
      "69": "Αυτό είναι απλά να σηκώνεις ένα κουτί και να το βάζεις\nσε ένα ράφι.",
      "70": "Ας το δοκιμάσουμε. 5 6 7.",
      "71": "Και σήκωσε το κουτί, βάλε το σε ένα ράφι.",
      "72": "5 6 7.",
      "73": "Και 1, τρία, πέντε, επτά.",
      "74": "Και 1, τρία, πέντε, επτά.",
      "75": "Και 1, τρία, πέντε.",
      "76": "Δες πώς πάνε οι αγκώνες μου και μετά τεντώνουν εδώ\nαπό τον αγκώνα.",
      "77": "Θα τεντώσω τα χέρια μου.",
      "78": "Αυτό είναι σαν να ρίχνεις ένα βελάκι.",
      "79": "Πολύ καλά.",
      "80": "Τώρα θα κάνουμε αυτό, αλλά ένα χέρι κάθε\nφορά.",
      "81": "Και πώς θα δουλέψει;",
      "82": "Θα είναι πάντα το αντίθετο χέρι\nαπό το πόδι μου.",
      "83": "Εντάξει;",
      "84": "Άρα πάω με το δεξί πόδι.",
      "85": "Θα πάω με το αριστερό χέρι.",
      "86": "Άρα θα πάω 5 6 7.",
      "87": "1 2 3.",
      "88": "Εντάξει;",
      "89": "5 6 7.",
      "90": "Και 1 2 3.",
      "91": "Βλέπεις υπάρχει λίγη έμφαση σε αυτόν τον\nμπροστινό count.",
      "92": "Άρα όταν τεντώνω, υπάρχει λίγη έμφαση\nεδώ.",
      "93": "Αυτό είναι αυτό που θέλω να σκεφτείς, να\nπροβάλλεις μπροστά.",
      "94": "Άρα αντί να το κάνεις απλά έτσι, βεβαιώσου ότι",
      "95": "κάνεις την πλήρη κίνηση.",
      "96": "Έρχεσαι πάνω.",
      "97": "Προβάλλεις μπροστά.",
      "98": "Και μετά χαλαρώνεις.",
      "99": "Φέρνεις το χέρι σου κάτω.",
      "100": "Εντάξει;",
      "101": "5 6 7.",
      "102": "1 2 3.",
      "103": "Και 5 6 7.",
      "104": "Και 1 2 3.",
      "105": "Και 5 6 7.",
      "106": "Και 1 2 3.",
      "107": "Και 5 6 7.",
      "108": "Εντάξει;",
      "109": "Τώρα θα το κάνουμε με το Footwork μας.",
      "110": "5 6 7.",
      "111": "Και 1 2 3.",
      "112": "Και 5 6 7.",
      "113": "Και 1 2 3.",
      "114": "5 6 7.",
      "115": "1 2 3.",
      "116": "Και 5 6 7.",
      "117": "Όταν κάθεσαι στην πλευρά.",
      "118": "1 2 3.",
      "119": "Πέντε.",
      "120": "Βλέπεις έχεις αυτή την κίνηση όπου ο αγκώνας σου\nθα",
      "121": "έρθει πρώτος.",
      "122": "Και μετά θα τεντώσεις.",
      "123": "Μετά θα πας κάτω.",
      "124": "Και θα επαναλάβεις.",
      "125": "Χέρια.",
      "126": "Η κίνηση τρένου choo-choo.",
      "127": "Τώρα τις παλιές μέρες στο Palladium, δεν ήξεραν\nπραγματικά",
      "128": "πώς να κουνάνε τα χέρια τους.",
      "129": "Δεν ήξεραν πραγματικά τι να κάνουν με τα\nχέρια τους.",
      "130": "Και να έχεις υπόψη, αυτοί ήταν χορευτές που\nδεν",
      "131": "ήταν κλασικά εκπαιδευμένοι.",
      "132": "Αλλά είχαν πολύ στιλ.",
      "133": "Πολλές γεύσεις.",
      "134": "Άρα χόρευαν έτσι με τα\nχέρια τους.",
      "135": "Και δεν ήξεραν πραγματικά ακριβώς τι\nνα κάνουν.",
      "136": "Δεν είχαν τη σωστή τεχνική.",
      "137": "Αλλά παρόλα αυτά το έκαναν να φαίνεται απίστευτο.",
      "138": "Άρα πραγματικά, σου συμβουλεύω να εξασκηθείς λίγο σε\nαυτό",
      "139": "στο βασικό σου.",
      "140": "Και τώρα, προσπάθησε να κάνεις τα Suzy Qs σου.",
      "141": "1 2 3, 5 6 7.",
      "142": "Και θυμήσου, αυτό είναι δεξί, αριστερό, δεξί\nμε τα χέρια.",
      "143": "Αριστερό, δεξί, αριστερό.",
      "144": "Και ίσως τις στροφές σου.",
      "145": "1 2 3, 5 6 7.",
      "146": "Ίσως το Left Turn σου.",
      "147": "1 2 3.",
      "148": "Δεξί, αριστερό, δεξί.",
      "149": "Βασικό.",
      "150": "Δύο, τρία, 5 6 7.",
      "151": "Εντάξει;",
      "152": "Εντάξει.",
      "153": "Θα εξασκηθούμε στο να κάνουμε αυτή την κίνηση\nλίγο",
      "154": "περισσότερο.",
      "155": "Και πάλι, σε προσκαλώ να πας τώρα πάνω σε όλα\nτα βήματα που",
      "156": "καλύψαμε.",
      "157": "Απλά ξανακάνε τα drills.",
      "158": "Και προσπάθησε να βάλεις αυτά τα χέρια σε\nόλα αυτά τα βήματα.",
      "159": "Άρα, 5 6 7.",
      "160": "Μόνο τα χέρια.",
      "161": "1 2 3.",
      "162": "Και αγκώνας, χέρι.",
      "163": "Αγκώνας, χέρι.",
      "164": "Αγκώνας, χέρι.",
      "165": "Επτά.",
      "166": "Και 1 2 3.",
      "167": "Πέντε, έξι.",
      "168": "Με το βήμα.",
      "169": "Και 1 2 3.",
      "170": "5 6 7.",
      "171": "Βεβαιώσου ότι η στάση σου είναι λίγο\nμπροστά.",
      "172": "Έξι, επτά.",
      "173": "1 2 3.",
      "174": "5 6 7.",
      "175": "1 2 3.",
      "176": "5 6 7.",
      "177": "1 2 3.",
      "178": "5 6 7.",
      "179": "1 2 3.",
      "180": "5 6 7.",
      "181": "1 2 3.",
      "182": "5 6 7.",
      "183": "Πολύ καλά, θα το κάνουμε ξανά, αλλά\nβεβαιώσου τώρα",
      "184": "θα πάμε πλάγια απλά για να βεβαιωθούμε\nότι.",
      "185": "Αυτός ο αγκώνας δεν έρχεται ποτέ πίσω από την πλάτη. Αυτό\nείναι ένα άλλο",
      "186": "λάθος που βλέπω πολύ, αυτοί οι άνθρωποι που χορεύουν.",
      "187": "Έτσι, και τώρα φαίνεται λίγο σαν να",
      "188": "κολυμπάω, αλλά δεν κολυμπάμε, είμαστε πάντα.",
      "189": "Κρατώντας τους αγκώνες μας μπροστά από το σώμα μας.\nΑυτό λέγεται",
      "190": "οβελιαίο επίπεδο, και γενικά όταν.",
      "191": "Χορεύεις περίπου 99.999% του χρόνου, θα",
      "192": "κρατάς όλες τις κινήσεις του χεριού σου στο\nοβελιαίο.",
      "193": "Επίπεδο, άρα εδώ δεν περνάς ποτέ πέρα\nαπό αυτό το εύρος",
      "194": "κίνησης, εντάξει; Άρα πραγματικά σε προσκαλώ να.",
      "195": "Σκέφτεσαι μπροστά, εδώ είναι όπου όλη η\nενέργειά σου είναι όταν",
      "196": "χορεύεις Salsa. Άρα ας το κάνουμε, πέντε, έξι,",
      "197": "Επτά, 1 2 3, 5 6 7. Πρόσεξε το στήθος μου είναι λίγο",
      "198": "μπροστά, 5 6 7,",
      "199": "1 2 3, 5 6 7, 1 2 3, 5 6 7. Πολύ καλά,\nας το κάνουμε άλλη μία",
      "200": "φορά.",
      "201": "5 6 7, βασικό, 1 2 3,",
      "202": "τα χέρια πάνε επτά, αριστερό, δεξί, αριστερό,",
      "203": "δεξί,",
      "204": "αριστερό, δεξί.",
      "205": "Βασικά είναι αντίθεση μεταξύ των χεριών\nκαι των ποδιών.",
      "206": "και 1 2 3, 5 6 7, ένα, δύο,",
      "207": "Τρία, μπορείς να φανταστείς ότι ρίχνεις\nένα βελάκι. 1 2 3,",
      "208": "5 6 7, 1 2 3.",
      "209": "Κράτα τους αγκώνες σου μπροστά",
      "210": "από το σώμα σου στο οβελιαίο",
      "211": "επίπεδο. Τρία, πέντε, έξι, μία ακόμη.",
      "212": "1 2 3, 5 6 7."
    }
  }
}
